Class sigma
{
field static int n
field static int sum
field static int index
method public static int fib(int )
max_stack 15
max_Locals 15
{
iload 0
sipush 2
isub
iflt L0
iconst_0
goto L1
L0: iconst_1
L1:
ifeq L2
iload 0
goto L3     
L2:
iload 0
sipush 1
isub
invokestatic int sigma.fib(int )
iload 0
sipush 2
isub
invokestatic int sigma.fib(int )
iadd
goto L3
L3:
ireturn
}
method public static void main(java.lang.String[])
max_stack 15
max_Locals 15
{
sipush 1
putstatic int  sigma.sum
sipush 0
putstatic int  sigma.index
sipush 1
putstatic int  sigma.n
L4:
getstatic int  sigma.n
sipush 10
isub
ifle L5
iconst_0
goto L6
L5: iconst_1
L6:
ifeq L7
getstatic java.io.PrintStream java.lang.System.out
ldc "sadasd"
invokevirtual void java.io.PrintStream.print(java.lang.String)
getstatic int  sigma.n
sipush 1
iadd
putstatic int  sigma.n
goto L4
L7:
getstatic java.io.PrintStream java.lang.System.out
ldc "The sum is"
invokevirtual void java.io.PrintStream.print(java.lang.String)
getstatic java.io.PrintStream java.lang.System.out
getstatic int  sigma.sum
invokevirtual void java.io.PrintStream.println(int)
getstatic java.io.PrintStream java.lang.System.out
getstatic int  sigma.index
invokevirtual void java.io.PrintStream.println(int)
sipush 0
istore 1
iload 1
sipush 0
isub
ifle L8
iconst_0
goto L9
L8: iconst_1
L9:
ifeq L10
getstatic java.io.PrintStream java.lang.System.out
ldc "i <= 0"
invokevirtual void java.io.PrintStream.println(java.lang.String)
getstatic int  sigma.sum
sipush 0
isub
ifeq L11
iconst_0
goto L12
L11: iconst_1
L12:
ifeq L13
getstatic java.io.PrintStream java.lang.System.out
ldc "sum=0"
invokevirtual void java.io.PrintStream.println(java.lang.String)
goto L14    
L13:
getstatic java.io.PrintStream java.lang.System.out
ldc "sum!=0"
invokevirtual void java.io.PrintStream.println(java.lang.String)
goto L14
L14:
goto L19    
L10:
iload 1
sipush 0
isub
ifge L16
iconst_0
goto L17
L16: iconst_1
L17:
ifeq L18
getstatic java.io.PrintStream java.lang.System.out
ldc "i>=0"
invokevirtual void java.io.PrintStream.println(java.lang.String)
goto L19    
L18:
getstatic java.io.PrintStream java.lang.System.out
ldc "i!= 1 or 0 "
invokevirtual void java.io.PrintStream.println(java.lang.String)
goto L19
L19:
sipush 10
putstatic int  sigma.sum
getstatic int  sigma.sum
L20:
sipush 10
isub
iflt L21
iconst_0
goto L22
L21: iconst_1
L22:
ifeq L23
getstatic java.io.PrintStream java.lang.System.out
getstatic int  sigma.index
invokevirtual void java.io.PrintStream.println(int)
getstatic int  sigma.index
sipush 1
iadd
putstatic int  sigma.index
sipush 0
istore 1
iload 1
L24:
sipush 10
isub
iflt L25
iconst_0
goto L26
L25: iconst_1
L26:
ifeq L27
getstatic java.io.PrintStream java.lang.System.out
iload 1
invokevirtual void java.io.PrintStream.print(int)
getstatic int  sigma.index
sipush 1
iadd
putstatic int  sigma.index
iload 1
sipush 1
iadd
istore 1
iload 1
goto L24
L27:
getstatic java.io.PrintStream java.lang.System.out
ldc ""
invokevirtual void java.io.PrintStream.println(java.lang.String)
getstatic int  sigma.sum
sipush 1
iadd
putstatic int  sigma.sum
getstatic int  sigma.sum
goto L20
L23:
getstatic java.io.PrintStream java.lang.System.out
getstatic int  sigma.index
invokevirtual void java.io.PrintStream.println(int)
sipush 0
istore 1
sipush 0
istore 1
iload 1
L28:
sipush 10
isub
iflt L29
iconst_0
goto L30
L29: iconst_1
L30:
ifeq L31
getstatic java.io.PrintStream java.lang.System.out
iload 1
invokestatic int sigma.fib(int )
invokevirtual void java.io.PrintStream.println(int)
iload 1
sipush 1
iadd
istore 1
iload 1
goto L28
L31:
return
}
}